fwpods_py/__init__.py
fwpods_py/fwpods.py
fwpods_py/swn_tree_manager.py
fwpods_py/utils.py
fwpods_py/weights_manager.py
fwpods_py/window_manager.py
fwpods_py-0.0.3.dist-info/LICENSE
fwpods_py-0.0.3.dist-info/METADATA
fwpods_py-0.0.3.dist-info/WHEEL
fwpods_py-0.0.3.dist-info/top_level.txt
fwpods_py-0.0.3.dist-info/RECORD
