Metadata-Version: 2.1
Name: fwpods_py
Version: 0.0.3
Summary: A python implementation on the FWPODS algorithm.
Author: Fishappy0
Author-email: <fishappy0@gmail.com>
Keywords: fwpods,data stream mining,stream mining,frequent weighted pattern data stream,sliding window over data streams
Classifier: Development Status :: 3 - Alpha
Classifier: Intended Audience :: Developers
Classifier: Operating System :: Unix
Classifier: Operating System :: Microsoft :: Windows
License-File: LICENSE
Requires-Dist: orderedset
